linalg_zero/__init__.py
linalg_zero/distillation.py
linalg_zero/generate.py
linalg_zero/grpo.py
linalg_zero/sft.py
linalg_zero/config/data.py
linalg_zero/config/dataset/default.yml
linalg_zero/config/dataset/default_debug.yml
linalg_zero/config/distillation/llamacpp_qwen3_30b_A3B_instruct.yaml
linalg_zero/config/distillation/llamacpp_qwen3_30b_A3B_think.yaml
linalg_zero/config/distillation/llamacpp_qwen3_32b_instruct.yaml
linalg_zero/config/distillation/qwen3_think_vllm_debug.yaml
linalg_zero/config/distillation/vllm_qwen3_32b.yaml
linalg_zero/config/distillation/vllm_qwen3_4b_think.yaml
linalg_zero/config/sft/sft_config.yaml
linalg_zero/config/sft/sft_debug_config.yaml
linalg_zero/config/sft/accelerate/zero2.yaml
linalg_zero/config/sft/accelerate/zero3.yaml
linalg_zero/distillation/__init__.py
linalg_zero/distillation/data.py
linalg_zero/distillation/launch_server.py
linalg_zero/distillation/utils.py
linalg_zero/distillation/components/diagnostics.py
linalg_zero/distillation/components/models.py
linalg_zero/distillation/components/multi_turn_generation.py
linalg_zero/distillation/components/multi_turn_generation_base.py
linalg_zero/distillation/llama-cpp/local.sh
linalg_zero/distillation/llama-cpp/runpod.sh
linalg_zero/distillation/scripts/__init__.py
linalg_zero/distillation/scripts/push_debug_dataset.py
linalg_zero/distillation/vllm/README.md
linalg_zero/distillation/vllm/tool_chat_template_deepseekr1.jinja
linalg_zero/distillation/vllm/tool_chat_template_hermes.jinja
linalg_zero/distillation/vllm/tool_chat_template_llama3.1_json.jinja
linalg_zero/distillation/vllm/tool_chat_template_mistral.jinja
linalg_zero/distillation/vllm/tool_chat_template_mistral_parallel.jinja
linalg_zero/generator/__init__.py
linalg_zero/generator/context.py
linalg_zero/generator/core.py
linalg_zero/generator/difficulty_config.py
linalg_zero/generator/entropy_control.py
linalg_zero/generator/generation_constraints.py
linalg_zero/generator/generator_factories.py
linalg_zero-0.3.0.dist-info/METADATA
linalg_zero-0.3.0.dist-info/WHEEL
linalg_zero-0.3.0.dist-info/licenses/LICENSE
linalg_zero-0.3.0.dist-info/RECORD
