Metadata-Version: 2.4
Name: linalg-zero
Version: 0.3.0
Summary: This repository provides tools to generate a linear algebra dataset and code to train an open-source pre-trained model. Our goal is to explore the model's potential for emergent reasoning, inspired by the Deepseek-R1 paper.
Project-URL: Homepage, https://atomwalk12.github.io/linalg-zero/
Project-URL: Repository, https://github.com/atomwalk12/linalg-zero
Project-URL: Documentation, https://atomwalk12.github.io/linalg-zero/
Author-email: Razvan Florian Vasile <atomwalk@duck.com>
License-File: LICENSE
Keywords: python
Classifier: Intended Audience :: Developers
Classifier: Programming Language :: Python
Classifier: Programming Language :: Python :: 3
Classifier: Programming Language :: Python :: 3.10
Classifier: Programming Language :: Python :: 3.11
Classifier: Programming Language :: Python :: 3.12
Classifier: Topic :: Software Development :: Libraries :: Python Modules
Requires-Python: <3.13,>=3.10
Requires-Dist: anyio>=4.9.0
Requires-Dist: argilla>=2.8.0
Requires-Dist: bitsandbytes>=0.46.1
Requires-Dist: bs4>=0.0.2
Requires-Dist: datasets>=4.0.0
Requires-Dist: deepspeed>=0.17.3
Requires-Dist: distilabel[instructor,openai,outlines]>=1.5.3
Requires-Dist: fastapi>=0.116.1
Requires-Dist: flashinfer-python>=0.3.1
Requires-Dist: huggingface-hub>=0.33.4
Requires-Dist: instructor>=1.9.2
Requires-Dist: ipykernel>=6.29.5
Requires-Dist: liger-kernel>=0.6.1
Requires-Dist: llama-cpp-python==0.3.13
Requires-Dist: math-verify>=0.8.0
Requires-Dist: matplotlib>=3.10.6
Requires-Dist: numpy>=1.26.4
Requires-Dist: outlines>=0.1.0
Requires-Dist: pydantic-settings>=2.10.1
Requires-Dist: pydantic>=2.11.7
Requires-Dist: pytest>=7.2.0
Requires-Dist: pyyaml>=6.0.2
Requires-Dist: sse-starlette>=2.4.1
Requires-Dist: starlette-context>=0.4.0
Requires-Dist: starlette>=0.47.1
Requires-Dist: sympy==1.14.0
Requires-Dist: transformers>=4.53.1
Requires-Dist: trl>=0.19.1
Requires-Dist: typing-extensions>=4.14.1
Requires-Dist: uvicorn>=0.35.0
Requires-Dist: verl>=0.5.0
Requires-Dist: vllm>=0.10.2
